odoo/addons/account_invoice_alternate_payer/README.rst
odoo/addons/account_invoice_alternate_payer/__init__.py
odoo/addons/account_invoice_alternate_payer/__manifest__.py
odoo/addons/account_invoice_alternate_payer/i18n/account_invoice_alternate_payer.pot
odoo/addons/account_invoice_alternate_payer/i18n/es.po
odoo/addons/account_invoice_alternate_payer/migrations/13.0.1.0.0/post-migration.py
odoo/addons/account_invoice_alternate_payer/models/__init__.py
odoo/addons/account_invoice_alternate_payer/models/account_move.py
odoo/addons/account_invoice_alternate_payer/models/account_payment.py
odoo/addons/account_invoice_alternate_payer/readme/CONTRIBUTORS.rst
odoo/addons/account_invoice_alternate_payer/readme/DESCRIPTION.rst
odoo/addons/account_invoice_alternate_payer/readme/USAGE.rst
odoo/addons/account_invoice_alternate_payer/static/description/icon.png
odoo/addons/account_invoice_alternate_payer/static/description/index.html
odoo/addons/account_invoice_alternate_payer/tests/__init__.py
odoo/addons/account_invoice_alternate_payer/tests/test_account_invoice.py
odoo/addons/account_invoice_alternate_payer/views/account_move_views.xml
odoo13_addon_account_invoice_alternate_payer-13.0.1.0.1.dev6.dist-info/METADATA
odoo13_addon_account_invoice_alternate_payer-13.0.1.0.1.dev6.dist-info/WHEEL
odoo13_addon_account_invoice_alternate_payer-13.0.1.0.1.dev6.dist-info/top_level.txt
odoo13_addon_account_invoice_alternate_payer-13.0.1.0.1.dev6.dist-info/RECORD
